odoo/addons/project_task_expense/README.rst
odoo/addons/project_task_expense/__init__.py
odoo/addons/project_task_expense/__manifest__.py
odoo/addons/project_task_expense/i18n/es.po
odoo/addons/project_task_expense/models/__init__.py
odoo/addons/project_task_expense/models/account_analytic_line.py
odoo/addons/project_task_expense/models/hr_expense.py
odoo/addons/project_task_expense/models/project_project.py
odoo/addons/project_task_expense/models/project_task.py
odoo/addons/project_task_expense/static/description/icon.png
odoo/addons/project_task_expense/views/hr_expense_view.xml
odoo/addons/project_task_expense/views/project_views.xml
odoo_addon_project_task_expense-16.0.1.0.0.4.dist-info/METADATA
odoo_addon_project_task_expense-16.0.1.0.0.4.dist-info/WHEEL
odoo_addon_project_task_expense-16.0.1.0.0.4.dist-info/top_level.txt
odoo_addon_project_task_expense-16.0.1.0.0.4.dist-info/RECORD
